{
  "id": "STREAMLINE_MODERNE",
  "label": "Streamline Moderne Civic Walk",
  "description": "Horizontal civic facade, curved terminal wall, arcade colonnade, approach ramp, balcony ribbon, round portal — no tower spines",
  "style": "streamline",
  "modules": [
    {"arch_type": "BAROQUE_FACADE", "overrides": {"baroque_facade_bays": 7, "baroque_facade_height": 9.0, "baroque_order": "DORIC", "baroque_ornament_density": 0.35, "material_choice": "AUTO"}},
    {"arch_type": "CURVED_WALL", "overrides": {"wall_arc_angle": 75.0, "wall_arc_radius": 6.0, "wall_height": 3.2, "wall_thickness": 0.4, "crenel_merlon_count": 6, "material_choice": "STONE"}},
    {"arch_type": "GB_ROMANESQUE_ARCADE", "overrides": {"gb_width": 3.4, "gb_height": 3.8, "gb_trim_mode": "RECESS", "unit_size": 3.4, "material_choice": "STONE"}},
    {"arch_type": "GREYBOX_RAMP", "overrides": {"gb_length": 9.0, "gb_width": 3.2, "gb_rise": 2.8, "gb_wall_thick": 0.3, "gb_curbs": true, "material_choice": "STONE", "unit_size": 2.0}},
    {"arch_type": "BALCONY", "overrides": {"balcony_width": 3.2, "balcony_depth": 0.85, "balcony_baluster_count": 14, "material_choice": "AUTO"}},
    {"arch_type": "ARCHWAY_ADV", "overrides": {"archway_style": "ROUND", "archway_width": 2.8, "archway_height": 3.0, "archway_depth": 0.55, "material_choice": "STONE"}}
  ]
}
